README.rst
setup.py
PySpinWarrior.egg-info/PKG-INFO
PySpinWarrior.egg-info/SOURCES.txt
PySpinWarrior.egg-info/dependency_links.txt
PySpinWarrior.egg-info/top_level.txt
spinwarrior/__init__.py