Metadata-Version: 1.0
Name: PySpinWarrior
Version: 0.2.3
Summary: SpinWarrior control
Home-page: http://phys.au.dk/forskning/forskningsomraader/amo/the-ion-trap-group/
Author: Michael V. DePalatis
Author-email: depalatis@phys.au.dk
License: UNKNOWN
Platform: UNKNOWN
